antlr4-stubs/BufferedTokenStream.pyi
antlr4-stubs/CommonTokenFactory.pyi
antlr4-stubs/CommonTokenStream.pyi
antlr4-stubs/FileStream.pyi
antlr4-stubs/InputStream.pyi
antlr4-stubs/IntervalSet.pyi
antlr4-stubs/LL1Analyzer.pyi
antlr4-stubs/Lexer.pyi
antlr4-stubs/ListTokenSource.pyi
antlr4-stubs/METADATA.toml
antlr4-stubs/Parser.pyi
antlr4-stubs/ParserInterpreter.pyi
antlr4-stubs/ParserRuleContext.pyi
antlr4-stubs/PredictionContext.pyi
antlr4-stubs/Recognizer.pyi
antlr4-stubs/RuleContext.pyi
antlr4-stubs/StdinStream.pyi
antlr4-stubs/Token.pyi
antlr4-stubs/TokenStreamRewriter.pyi
antlr4-stubs/Utils.pyi
antlr4-stubs/__init__.pyi
antlr4-stubs/_pygrun.pyi
antlr4-stubs/py.typed
antlr4-stubs/atn/ATN.pyi
antlr4-stubs/atn/ATNConfig.pyi
antlr4-stubs/atn/ATNConfigSet.pyi
antlr4-stubs/atn/ATNDeserializationOptions.pyi
antlr4-stubs/atn/ATNDeserializer.pyi
antlr4-stubs/atn/ATNSimulator.pyi
antlr4-stubs/atn/ATNState.pyi
antlr4-stubs/atn/ATNType.pyi
antlr4-stubs/atn/LexerATNSimulator.pyi
antlr4-stubs/atn/LexerAction.pyi
antlr4-stubs/atn/LexerActionExecutor.pyi
antlr4-stubs/atn/ParserATNSimulator.pyi
antlr4-stubs/atn/PredictionMode.pyi
antlr4-stubs/atn/SemanticContext.pyi
antlr4-stubs/atn/Transition.pyi
antlr4-stubs/atn/__init__.pyi
antlr4-stubs/dfa/DFA.pyi
antlr4-stubs/dfa/DFASerializer.pyi
antlr4-stubs/dfa/DFAState.pyi
antlr4-stubs/dfa/__init__.pyi
antlr4-stubs/error/DiagnosticErrorListener.pyi
antlr4-stubs/error/ErrorListener.pyi
antlr4-stubs/error/ErrorStrategy.pyi
antlr4-stubs/error/Errors.pyi
antlr4-stubs/error/__init__.pyi
antlr4-stubs/tree/Chunk.pyi
antlr4-stubs/tree/ParseTreeMatch.pyi
antlr4-stubs/tree/ParseTreePattern.pyi
antlr4-stubs/tree/ParseTreePatternMatcher.pyi
antlr4-stubs/tree/RuleTagToken.pyi
antlr4-stubs/tree/TokenTagToken.pyi
antlr4-stubs/tree/Tree.pyi
antlr4-stubs/tree/Trees.pyi
antlr4-stubs/tree/__init__.pyi
antlr4-stubs/xpath/XPath.pyi
antlr4-stubs/xpath/XPathLexer.pyi
antlr4-stubs/xpath/__init__.pyi
types_antlr4_python3_runtime-4.13.0.20250822.dist-info/licenses/LICENSE
types_antlr4_python3_runtime-4.13.0.20250822.dist-info/METADATA
types_antlr4_python3_runtime-4.13.0.20250822.dist-info/WHEEL
types_antlr4_python3_runtime-4.13.0.20250822.dist-info/top_level.txt
types_antlr4_python3_runtime-4.13.0.20250822.dist-info/RECORD
